<?xml version="1.0" encoding="UTF-8"?>
<factura id="comprobante" version="1.1.0">
  <infoTributaria>
    <ambiente>2</ambiente>
    <tipoEmision>1</tipoEmision>
    <razonSocial>FUNDACION DE AYUDA SOCIAL BANCO DE ALIMENTOS</razonSocial>
    <nombreComercial>BANCO DE ALIMENTOS QUITO</nombreComercial>
    <ruc>1791921429001</ruc>
    <claveAcceso>1905202501179192142900129999980000003741234567815</claveAcceso>
    <codDoc>01</codDoc>
    <estab>999</estab>
    <ptoEmi>998</ptoEmi>
    <secuencial>000000374</secuencial>
    <dirMatriz>Av Pedro Vicente Maldonado S15238 y Balzar</dirMatriz>
  </infoTributaria>
  <infoFactura>
    <fechaEmision>19/05/2025</fechaEmision>
    <dirEstablecimiento>Av Pedro Vicente Maldonado S15238 y Balzar</dirEstablecimiento>
    <obligadoContabilidad>SI</obligadoContabilidad>
    <tipoIdentificacionComprador>04</tipoIdentificacionComprador>
    <razonSocialComprador>CENTRO INTEGRAL BILINGÜE MI HOGAR DE CHOCOLATE</razonSocialComprador>
    <identificacionComprador>1707122022001</identificacionComprador>
    <totalSinImpuestos>4.00</totalSinImpuestos>
    <totalDescuento>0.00</totalDescuento>
    <totalConImpuestos>
      <totalImpuesto>
        <codigo>2</codigo>
        <codigoPorcentaje>0</codigoPorcentaje>
        <descuentoAdicional>0.00</descuentoAdicional>
        <baseImponible>4.00</baseImponible>
        <valor>0.00</valor>
      </totalImpuesto>
    </totalConImpuestos>
    <propina>0.00</propina>
    <importeTotal>4.00</importeTotal>
    <moneda>DOLAR</moneda>
    <pagos>
      <pago>
        <formaPago>01</formaPago>
        <total>4.00</total>
      </pago>
    </pagos>
  </infoFactura>
  <detalles>
    <detalle>
      <codigoPrincipal>roductos lácteos/Da</codigoPrincipal>
      <descripcion>LACTEOS</descripcion>
      <unidadMedida>DOLAR</unidadMedida>
      <cantidad>10.000000</cantidad>
      <precioUnitario>0.400000</precioUnitario>
      <descuento>0.00</descuento>
      <precioTotalSinImpuesto>4.00</precioTotalSinImpuesto>
      <impuestos>
        <impuesto>
          <codigo>2</codigo>
          <codigoPorcentaje>0</codigoPorcentaje>
          <tarifa>0</tarifa>
          <baseImponible>4.00</baseImponible>
          <valor>0.00</valor>
        </impuesto>
      </impuestos>
    </detalle>
  </detalles>
  <infoAdicional>
    <campoAdicional nombre="Direccion">GONZALO PEREZ BUSTAMANTE</campoAdicional>
    <campoAdicional nombre="Telefono">0983468934</campoAdicional>
    <campoAdicional nombre="Email">LIBERTADOR48@HOTMAILCOM</campoAdicional>
    <campoAdicional nombre="Referencia">OLGA LUCERO</campoAdicional>
    <campoAdicional nombre="tipoContribuyente">Contribuyente Regimen General</campoAdicional>
    <campoAdicional nombre="serieEstablecimiento">999998</campoAdicional>
    <campoAdicional nombre="PlacaVehiculo">.</campoAdicional>
    <campoAdicional nombre="CtaEstablecimiento">.</campoAdicional>
  </infoAdicional>
</factura>
